LICENSE
README.md
setup.py
extractnum/__init__.py
extractnum/main.py
extractnum.egg-info/PKG-INFO
extractnum.egg-info/SOURCES.txt
extractnum.egg-info/dependency_links.txt
extractnum.egg-info/entry_points.txt
extractnum.egg-info/requires.txt
extractnum.egg-info/top_level.txt