Metadata-Version: 2.1
Name: extractnum
Version: 1.0.0
Summary: A CLI for extracting number arrays from an unstructured log file and plotting results.
Home-page: UNKNOWN
Author: Keytoyze
Author-email: cmx_1007@foxmail.com
License: UNKNOWN
Platform: UNKNOWN
License-File: LICENSE
